MANIFEST.in
README.rst
setup.py
_interface/pyparport.c
pyparport/__init__.py
pyparport/__init__.pyc
pyparport.egg-info/PKG-INFO
pyparport.egg-info/SOURCES.txt
pyparport.egg-info/dependency_links.txt
pyparport.egg-info/top_level.txt
pyparport/__pycache__/__init__.cpython-34.pyc