Metadata-Version: 1.0
Name: pyparport
Version: 0.6
Summary: This module provides the possibility to connect to the first parallel port from Python.
Home-page: UNKNOWN
Author: Christian Kokoska
Author-email: christian@softcreate.de
License: GPLv3
Platform: UNKNOWN
